ibkr_report/__init__.py
ibkr_report/__main__.py
ibkr_report/cron.py
ibkr_report/definitions.py
ibkr_report/exchangerates.py
ibkr_report/report.py
ibkr_report/storage.py
ibkr_report/tools.py
ibkr_report/trade.py
ibkr_report/website.py
ibkr_report/static/css/main.css
ibkr_report/static/images/custom_statement.png
ibkr_report/static/images/run_statement.png
ibkr_report/static/js/main.js
ibkr_report/templates/base.html
ibkr_report/templates/error.html
ibkr_report/templates/index.html
ibkr_report/templates/result.html
tests/__init__.py
tests/test_cron.py
tests/test_exchange.py
tests/test_report.py
tests/test_smoke.py
tests/test_storage.py
ibkr_report_parser-2023.5.2.dist-info/LICENSE
ibkr_report_parser-2023.5.2.dist-info/METADATA
ibkr_report_parser-2023.5.2.dist-info/WHEEL
ibkr_report_parser-2023.5.2.dist-info/entry_points.txt
ibkr_report_parser-2023.5.2.dist-info/top_level.txt
ibkr_report_parser-2023.5.2.dist-info/RECORD
