Metadata-Version: 2.1
Name: ibkr-report-parser
Version: 2023.5.2
Summary: Interactive Brokers (IBKR) Report Parser for MyTax (vero.fi)
Home-page: https://github.com/oittaa/ibkr-report-parser
Author: Oittaa
Author-email: 
Keywords: Interactive Brokers,IBKR,OmaVero,MyTax,vero.fi
Classifier: Development Status :: 4 - Beta
Classifier: Intended Audience :: Other Audience
Classifier: License :: OSI Approved :: GNU General Public License v3 or later (GPLv3+)
Classifier: Operating System :: OS Independent
Classifier: Programming Language :: Python
Classifier: Programming Language :: Python :: 3
Classifier: Programming Language :: Python :: 3.8
Classifier: Programming Language :: Python :: 3.9
Classifier: Programming Language :: Python :: 3.10
Classifier: Programming Language :: Python :: 3.11
Requires-Python: >=3.8
License-File: LICENSE
Requires-Dist: flask (==2.3.2)
Provides-Extra: aws
Requires-Dist: boto3 (==1.26.124) ; extra == 'aws'
Provides-Extra: docker
Requires-Dist: gunicorn (==20.1.0) ; extra == 'docker'
Provides-Extra: gcp
Requires-Dist: google-cloud-storage (==2.8.0) ; extra == 'gcp'
